xdeps-0.10.7.dist-info/RECORD
xdeps-0.10.7.dist-info/LICENSE
xdeps-0.10.7.dist-info/WHEEL
xdeps-0.10.7.dist-info/top_level.txt
xdeps-0.10.7.dist-info/METADATA
xdeps/functions.py
xdeps/tasks.py
xdeps/_version.py
xdeps/sorting.py
xdeps/__init__.py
xdeps/refs.cpython-38-darwin.so
xdeps/utils.py
xdeps/refs.py
xdeps/table.py
xdeps/generate_refs.py
xdeps/madxutils.py
xdeps/general.py
xdeps/optimize/optimize.py
xdeps/optimize/jacobian.py
xdeps/optimize/matrixutils.py
xdeps/optimize/__init__.py
